odoo/addons/partner_coc/README.rst
odoo/addons/partner_coc/__init__.py
odoo/addons/partner_coc/__manifest__.py
odoo/addons/partner_coc/data/res_partner_id_category_data.xml
odoo/addons/partner_coc/i18n/am.po
odoo/addons/partner_coc/i18n/ar.po
odoo/addons/partner_coc/i18n/bg.po
odoo/addons/partner_coc/i18n/bs.po
odoo/addons/partner_coc/i18n/ca.po
odoo/addons/partner_coc/i18n/cs.po
odoo/addons/partner_coc/i18n/cs_CZ.po
odoo/addons/partner_coc/i18n/da.po
odoo/addons/partner_coc/i18n/de.po
odoo/addons/partner_coc/i18n/el_GR.po
odoo/addons/partner_coc/i18n/en_GB.po
odoo/addons/partner_coc/i18n/es.po
odoo/addons/partner_coc/i18n/es_CR.po
odoo/addons/partner_coc/i18n/es_EC.po
odoo/addons/partner_coc/i18n/es_MX.po
odoo/addons/partner_coc/i18n/es_VE.po
odoo/addons/partner_coc/i18n/et.po
odoo/addons/partner_coc/i18n/eu.po
odoo/addons/partner_coc/i18n/fi.po
odoo/addons/partner_coc/i18n/fr.po
odoo/addons/partner_coc/i18n/fr_CA.po
odoo/addons/partner_coc/i18n/fr_CH.po
odoo/addons/partner_coc/i18n/gl.po
odoo/addons/partner_coc/i18n/hr.po
odoo/addons/partner_coc/i18n/hr_HR.po
odoo/addons/partner_coc/i18n/hu.po
odoo/addons/partner_coc/i18n/it.po
odoo/addons/partner_coc/i18n/ja.po
odoo/addons/partner_coc/i18n/lt.po
odoo/addons/partner_coc/i18n/lv.po
odoo/addons/partner_coc/i18n/mk.po
odoo/addons/partner_coc/i18n/mn.po
odoo/addons/partner_coc/i18n/nb.po
odoo/addons/partner_coc/i18n/nb_NO.po
odoo/addons/partner_coc/i18n/nl.po
odoo/addons/partner_coc/i18n/nl_BE.po
odoo/addons/partner_coc/i18n/nl_NL.po
odoo/addons/partner_coc/i18n/partner_coc.pot
odoo/addons/partner_coc/i18n/pl.po
odoo/addons/partner_coc/i18n/pt.po
odoo/addons/partner_coc/i18n/pt_BR.po
odoo/addons/partner_coc/i18n/pt_PT.po
odoo/addons/partner_coc/i18n/ro.po
odoo/addons/partner_coc/i18n/ru.po
odoo/addons/partner_coc/i18n/sk.po
odoo/addons/partner_coc/i18n/sl.po
odoo/addons/partner_coc/i18n/sr@latin.po
odoo/addons/partner_coc/i18n/sv.po
odoo/addons/partner_coc/i18n/th.po
odoo/addons/partner_coc/i18n/tr.po
odoo11_addon_partner_coc-11.0.1.0.0.99.dev7.dist-info/METADATA
odoo11_addon_partner_coc-11.0.1.0.0.99.dev7.dist-info/WHEEL
odoo11_addon_partner_coc-11.0.1.0.0.99.dev7.dist-info/top_level.txt
odoo11_addon_partner_coc-11.0.1.0.0.99.dev7.dist-info/RECORD
